fourier_robot_descriptions/__init__.py
fourier_robot_descriptions/_cache.py
fourier_robot_descriptions/_package_dirs.py
fourier_robot_descriptions/_repositories.py
fourier_robot_descriptions/fourier.py
fourier_robot_descriptions/generate.py
fourier_robot_descriptions/assets/.gitignore
fourier_robot_descriptions/assets/base_urdf/fourier_left_hand_12dof.urdf
fourier_robot_descriptions/assets/base_urdf/fourier_left_hand_12dof_v1.urdf
fourier_robot_descriptions/assets/base_urdf/fourier_left_hand_6dof.urdf
fourier_robot_descriptions/assets/base_urdf/fourier_right_hand_12dof.urdf
fourier_robot_descriptions/assets/base_urdf/fourier_right_hand_12dof_v1.urdf
fourier_robot_descriptions/assets/base_urdf/fourier_right_hand_6dof.urdf
fourier_robot_descriptions/assets/base_urdf/gr1t1.urdf
fourier_robot_descriptions/assets/base_urdf/gr1t2.urdf
fourier_robot_descriptions/assets/base_urdf/gr2t2.urdf
fourier_robot_descriptions/assets/base_urdf/gr2t2d.urdf
fourier_robot_descriptions/assets/base_urdf/gr2t2v2.urdf
fourier_robot_descriptions/assets/base_urdf/gr3.urdf
fourier_robot_descriptions/assets/base_urdf/inspire_left_hand.urdf
fourier_robot_descriptions/assets/base_urdf/inspire_right_hand.urdf
fourier_robot_descriptions/assets/base_urdf/qinglong.urdf
fourier_robot_descriptions/assets/meshes/fourier_hand_12dof/L_hand_base_link.STL
fourier_robot_descriptions/assets/meshes/fourier_hand_12dof/L_index_intermediate_link.STL
fourier_robot_descriptions/assets/meshes/fourier_hand_12dof/L_index_metacarpal_link.STL
fourier_robot_descriptions/assets/meshes/fourier_hand_12dof/L_index_proximal_link.STL
fourier_robot_descriptions/assets/meshes/fourier_hand_12dof/L_middle_intermediate_link.STL
fourier_robot_descriptions/assets/meshes/fourier_hand_12dof/L_middle_proximal_link.STL
fourier_robot_descriptions/assets/meshes/fourier_hand_12dof/L_pinky_intermediate_link.STL
fourier_robot_descriptions/assets/meshes/fourier_hand_12dof/L_pinky_proximal_link.STL
fourier_robot_descriptions-0.2.7.dist-info/METADATA
fourier_robot_descriptions-0.2.7.dist-info/WHEEL
fourier_robot_descriptions-0.2.7.dist-info/licenses/LICENSE
fourier_robot_descriptions-0.2.7.dist-info/RECORD
